{
    "domain":"fn-blocksworld",
    "instance":"instance_6_2",
    "planners_data":{
        "./nfs-planner.bin --max_novelty 1 ":{
            "eval_per_second":440437.5625,
            "exit_code":0,
            "expanded":135,
            "generated":1087,
            "max_num_goals_sat":6,
            "novelty_histogram":{
                "0":{
                    "0":0,
                    "1":1
                },
                "1":{
                    "0":0,
                    "1":6
                },
                "2":{
                    "0":23,
                    "1":19
                },
                "3":{
                    "0":136,
                    "1":29
                },
                "4":{
                    "0":285,
                    "1":30
                },
                "5":{
                    "0":285,
                    "1":30
                },
                "6":{
                    "0":116,
                    "1":25
                }
            },
            "num_features":13,
            "num_goals":6,
            "plan":[
                "move-to-table(b4, b5)",
                "move-to-table(b5, b3)",
                "move-to-table(b3, b1)",
                "move-to-block(b1, b6, b4)",
                "move-to-table(b6, b2)",
                "move-to-block(b2, table, b5)",
                "move-to-block(b1, b4, b6)",
                "move-to-block(b4, table, b1)",
                "move-to-block(b2, b5, b4)",
                "move-to-block(b5, table, b2)"
            ],
            "search_time":0.002468,
            "solved":true,
            "valid":true,
            "wall_time":0.020000000000003126
        },
        "./nfs-planner.bin --max_novelty 1  --use_goal 0":{
            "eval_per_second":458649.8125,
            "exit_code":0,
            "expanded":135,
            "generated":1087,
            "max_num_goals_sat":6,
            "novelty_histogram":{
                "0":{
                    "0":0,
                    "1":1
                },
                "1":{
                    "0":0,
                    "1":6
                },
                "2":{
                    "0":23,
                    "1":19
                },
                "3":{
                    "0":136,
                    "1":29
                },
                "4":{
                    "0":285,
                    "1":30
                },
                "5":{
                    "0":285,
                    "1":30
                },
                "6":{
                    "0":116,
                    "1":25
                }
            },
            "num_features":12,
            "num_goals":6,
            "plan":[
                "move-to-table(b4, b5)",
                "move-to-table(b5, b3)",
                "move-to-table(b3, b1)",
                "move-to-block(b1, b6, b4)",
                "move-to-table(b6, b2)",
                "move-to-block(b2, table, b5)",
                "move-to-block(b1, b4, b6)",
                "move-to-block(b4, table, b1)",
                "move-to-block(b2, b5, b4)",
                "move-to-block(b5, table, b2)"
            ],
            "search_time":0.00237,
            "solved":true,
            "valid":true,
            "wall_time":0.00999999999999801
        },
        "./nfs-planner.bin --max_novelty 1  --use_state_vars 0 --use_goal 0 --use_actions 1":{
            "eval_per_second":69861.46875,
            "exit_code":0,
            "expanded":332,
            "generated":2350,
            "max_num_goals_sat":6,
            "novelty_histogram":{
                "0":{
                    "0":0,
                    "1":1
                },
                "1":{
                    "0":0,
                    "1":6
                },
                "2":{
                    "0":8,
                    "1":32
                },
                "3":{
                    "0":157,
                    "1":77
                },
                "4":{
                    "0":519,
                    "1":72
                },
                "5":{
                    "0":536,
                    "1":80
                },
                "6":{
                    "0":273,
                    "1":79
                }
            },
            "num_features":180,
            "num_goals":6,
            "plan":[
                "move-to-table(b4, b5)",
                "move-to-table(b5, b3)",
                "move-to-table(b3, b1)",
                "move-to-block(b1, b6, b5)",
                "move-to-table(b6, b2)",
                "move-to-block(b1, b5, b6)",
                "move-to-block(b4, table, b1)",
                "move-to-block(b2, table, b4)",
                "move-to-block(b5, table, b2)"
            ],
            "search_time":0.033638,
            "solved":true,
            "valid":true,
            "wall_time":0.03999999999996362
        },
        "./nfs-planner.bin --max_novelty 2 ":{
            "eval_per_second":172411.828125,
            "exit_code":0,
            "expanded":448,
            "generated":3006,
            "max_num_goals_sat":6,
            "novelty_histogram":{
                "0":{
                    "0":0,
                    "1":1,
                    "2":0
                },
                "1":{
                    "0":0,
                    "1":7,
                    "2":0
                },
                "2":{
                    "0":0,
                    "1":22,
                    "2":27
                },
                "3":{
                    "0":34,
                    "1":28,
                    "2":123
                },
                "4":{
                    "0":241,
                    "1":29,
                    "2":215
                },
                "5":{
                    "0":583,
                    "1":30,
                    "2":224
                },
                "6":{
                    "0":236,
                    "1":24,
                    "2":140
                }
            },
            "num_features":13,
            "num_goals":6,
            "plan":[
                "move-to-table(b4, b5)",
                "move-to-table(b5, b3)",
                "move-to-table(b3, b1)",
                "move-to-block(b1, b6, b5)",
                "move-to-table(b6, b2)",
                "move-to-block(b1, b5, b6)",
                "move-to-block(b4, table, b1)",
                "move-to-block(b2, table, b4)",
                "move-to-block(b5, table, b2)"
            ],
            "search_time":0.017435,
            "solved":true,
            "valid":true,
            "wall_time":0.03999999999950887
        },
        "./nfs-planner.bin --max_novelty 2  --use_goal 0":{
            "eval_per_second":196547.671875,
            "exit_code":0,
            "expanded":448,
            "generated":3006,
            "max_num_goals_sat":6,
            "novelty_histogram":{
                "0":{
                    "0":0,
                    "1":1,
                    "2":0
                },
                "1":{
                    "0":0,
                    "1":7,
                    "2":0
                },
                "2":{
                    "0":0,
                    "1":22,
                    "2":27
                },
                "3":{
                    "0":34,
                    "1":28,
                    "2":123
                },
                "4":{
                    "0":241,
                    "1":29,
                    "2":215
                },
                "5":{
                    "0":583,
                    "1":30,
                    "2":224
                },
                "6":{
                    "0":236,
                    "1":24,
                    "2":140
                }
            },
            "num_features":12,
            "num_goals":6,
            "plan":[
                "move-to-table(b4, b5)",
                "move-to-table(b5, b3)",
                "move-to-table(b3, b1)",
                "move-to-block(b1, b6, b5)",
                "move-to-table(b6, b2)",
                "move-to-block(b1, b5, b6)",
                "move-to-block(b4, table, b1)",
                "move-to-block(b2, table, b4)",
                "move-to-block(b5, table, b2)"
            ],
            "search_time":0.015294,
            "solved":true,
            "valid":true,
            "wall_time":0.010000000000218279
        },
        "./nfs-planner.bin --max_novelty 2  --use_state_vars 0 --use_goal 0 --use_actions 1":{
            "eval_per_second":533.859558,
            "exit_code":0,
            "expanded":325,
            "generated":2306,
            "max_num_goals_sat":6,
            "novelty_histogram":{
                "0":{
                    "0":0,
                    "1":1,
                    "2":0
                },
                "1":{
                    "0":0,
                    "1":6,
                    "2":0
                },
                "2":{
                    "0":0,
                    "1":34,
                    "2":8
                },
                "3":{
                    "0":0,
                    "1":71,
                    "2":93
                },
                "4":{
                    "0":0,
                    "1":71,
                    "2":261
                },
                "5":{
                    "0":8,
                    "1":76,
                    "2":266
                },
                "6":{
                    "0":0,
                    "1":80,
                    "2":170
                }
            },
            "num_features":180,
            "num_goals":6,
            "plan":[
                "move-to-table(b4, b5)",
                "move-to-table(b5, b3)",
                "move-to-table(b3, b1)",
                "move-to-block(b1, b6, b5)",
                "move-to-table(b6, b2)",
                "move-to-block(b1, b5, b6)",
                "move-to-block(b4, table, b1)",
                "move-to-block(b2, table, b4)",
                "move-to-block(b5, table, b2)"
            ],
            "search_time":4.31949,
            "solved":true,
            "valid":true,
            "wall_time":4.399999999999636
        },
        "./nfs-planner.bin --max_novelty 3 ":{
            "eval_per_second":48219.117188,
            "exit_code":0,
            "expanded":376,
            "generated":2602,
            "max_num_goals_sat":6,
            "novelty_histogram":{
                "0":{
                    "0":0,
                    "1":1,
                    "2":0,
                    "3":0
                },
                "1":{
                    "0":0,
                    "1":7,
                    "2":0,
                    "3":0
                },
                "2":{
                    "0":0,
                    "1":23,
                    "2":27,
                    "3":0
                },
                "3":{
                    "0":0,
                    "1":28,
                    "2":115,
                    "3":14
                },
                "4":{
                    "0":1,
                    "1":29,
                    "2":209,
                    "3":97
                },
                "5":{
                    "0":8,
                    "1":30,
                    "2":215,
                    "3":231
                },
                "6":{
                    "0":8,
                    "1":24,
                    "2":127,
                    "3":107
                }
            },
            "num_features":13,
            "num_goals":6,
            "plan":[
                "move-to-table(b4, b5)",
                "move-to-table(b5, b3)",
                "move-to-table(b3, b1)",
                "move-to-block(b1, b6, b5)",
                "move-to-table(b6, b2)",
                "move-to-block(b1, b5, b6)",
                "move-to-block(b4, table, b1)",
                "move-to-block(b2, table, b4)",
                "move-to-block(b5, table, b2)"
            ],
            "search_time":0.053962,
            "solved":true,
            "valid":true,
            "wall_time":0.06000000000040018
        },
        "./nfs-planner.bin --max_novelty 3  --use_goal 0":{
            "eval_per_second":42618.707031,
            "exit_code":0,
            "expanded":376,
            "generated":2602,
            "max_num_goals_sat":6,
            "novelty_histogram":{
                "0":{
                    "0":0,
                    "1":1,
                    "2":0,
                    "3":0
                },
                "1":{
                    "0":0,
                    "1":7,
                    "2":0,
                    "3":0
                },
                "2":{
                    "0":0,
                    "1":23,
                    "2":27,
                    "3":0
                },
                "3":{
                    "0":0,
                    "1":28,
                    "2":115,
                    "3":14
                },
                "4":{
                    "0":1,
                    "1":29,
                    "2":209,
                    "3":97
                },
                "5":{
                    "0":8,
                    "1":30,
                    "2":215,
                    "3":231
                },
                "6":{
                    "0":8,
                    "1":24,
                    "2":127,
                    "3":107
                }
            },
            "num_features":12,
            "num_goals":6,
            "plan":[
                "move-to-table(b4, b5)",
                "move-to-table(b5, b3)",
                "move-to-table(b3, b1)",
                "move-to-block(b1, b6, b5)",
                "move-to-table(b6, b2)",
                "move-to-block(b1, b5, b6)",
                "move-to-block(b4, table, b1)",
                "move-to-block(b2, table, b4)",
                "move-to-block(b5, table, b2)"
            ],
            "search_time":0.061053,
            "solved":true,
            "valid":true,
            "wall_time":0.07999999999992724
        },
        "./nfs-planner.bin --max_novelty 3  --use_state_vars 0 --use_goal 0 --use_actions 1":{
            "exit_code":34304,
            "wall_time":61.22000000000003
        },
        "./nfs-planner.bin --max_novelty 4 ":{
            "eval_per_second":6937.660645,
            "exit_code":0,
            "expanded":393,
            "generated":2713,
            "max_num_goals_sat":6,
            "novelty_histogram":{
                "0":{
                    "0":0,
                    "1":1,
                    "2":0,
                    "3":0,
                    "4":0
                },
                "1":{
                    "0":0,
                    "1":7,
                    "2":0,
                    "3":0,
                    "4":0
                },
                "2":{
                    "0":0,
                    "1":23,
                    "2":27,
                    "3":0,
                    "4":0
                },
                "3":{
                    "0":0,
                    "1":28,
                    "2":118,
                    "3":18,
                    "4":0
                },
                "4":{
                    "0":0,
                    "1":29,
                    "2":211,
                    "3":109,
                    "4":1
                },
                "5":{
                    "0":0,
                    "1":30,
                    "2":216,
                    "3":242,
                    "4":5
                },
                "6":{
                    "0":0,
                    "1":24,
                    "2":129,
                    "3":111,
                    "4":5
                }
            },
            "num_features":13,
            "num_goals":6,
            "plan":[
                "move-to-table(b4, b5)",
                "move-to-table(b5, b3)",
                "move-to-table(b3, b1)",
                "move-to-block(b1, b6, b5)",
                "move-to-table(b6, b2)",
                "move-to-block(b1, b5, b6)",
                "move-to-block(b4, table, b1)",
                "move-to-block(b2, table, b4)",
                "move-to-block(b5, table, b2)"
            ],
            "search_time":0.391054,
            "solved":true,
            "valid":true,
            "wall_time":0.43000000000029104
        },
        "./nfs-planner.bin --max_novelty 4  --use_goal 0":{
            "eval_per_second":8997.954102,
            "exit_code":0,
            "expanded":393,
            "generated":2713,
            "max_num_goals_sat":6,
            "novelty_histogram":{
                "0":{
                    "0":0,
                    "1":1,
                    "2":0,
                    "3":0,
                    "4":0
                },
                "1":{
                    "0":0,
                    "1":7,
                    "2":0,
                    "3":0,
                    "4":0
                },
                "2":{
                    "0":0,
                    "1":23,
                    "2":27,
                    "3":0,
                    "4":0
                },
                "3":{
                    "0":0,
                    "1":28,
                    "2":118,
                    "3":18,
                    "4":0
                },
                "4":{
                    "0":0,
                    "1":29,
                    "2":211,
                    "3":109,
                    "4":1
                },
                "5":{
                    "0":0,
                    "1":30,
                    "2":216,
                    "3":242,
                    "4":5
                },
                "6":{
                    "0":0,
                    "1":24,
                    "2":129,
                    "3":111,
                    "4":5
                }
            },
            "num_features":12,
            "num_goals":6,
            "plan":[
                "move-to-table(b4, b5)",
                "move-to-table(b5, b3)",
                "move-to-table(b3, b1)",
                "move-to-block(b1, b6, b5)",
                "move-to-table(b6, b2)",
                "move-to-block(b1, b5, b6)",
                "move-to-block(b4, table, b1)",
                "move-to-block(b2, table, b4)",
                "move-to-block(b5, table, b2)"
            ],
            "search_time":0.301513,
            "solved":true,
            "valid":true,
            "wall_time":0.33999999999969077
        }
    }
}